{"nodes": [{"id": "c_users_user_desktop_imaginehack_backend_tests_test_mcp_log_py", "label": "test_mcp_log.py", "file_type": "code", "source_file": "backend/tests/test_mcp_log.py", "source_location": "L1"}, {"id": "tests_test_mcp_log_schema", "label": "_schema()", "file_type": "code", "source_file": "backend/tests/test_mcp_log.py", "source_location": "L38"}, {"id": "tests_test_mcp_log_test_registry_execute_logs_connector_invocation", "label": "test_registry_execute_logs_connector_invocation()", "file_type": "code", "source_file": "backend/tests/test_mcp_log.py", "source_location": "L46"}, {"id": "tests_test_mcp_log_test_registry_without_logging_does_not_record", "label": "test_registry_without_logging_does_not_record()", "file_type": "code", "source_file": "backend/tests/test_mcp_log.py", "source_location": "L70"}, {"id": "tests_test_mcp_log_test_list_mcp_log_filters_by_workload_and_orders_recent_first", "label": "test_list_mcp_log_filters_by_workload_and_orders_recent_first()", "file_type": "code", "source_file": "backend/tests/test_mcp_log.py", "source_location": "L80"}, {"id": "tests_test_mcp_log_client", "label": "client()", "file_type": "code", "source_file": "backend/tests/test_mcp_log.py", "source_location": "L105"}, {"id": "tests_test_mcp_log_test_get_mcp_log_endpoint_returns_bare_list", "label": "test_get_mcp_log_endpoint_returns_bare_list()", "file_type": "code", "source_file": "backend/tests/test_mcp_log.py", "source_location": "L111"}, {"id": "tests_test_mcp_log_test_get_mcp_log_endpoint_filters_by_workload", "label": "test_get_mcp_log_endpoint_filters_by_workload()", "file_type": "code", "source_file": "backend/tests/test_mcp_log.py", "source_location": "L138"}, {"id": "tests_test_mcp_log_rationale_1", "label": "Tests for the MCP activity log (task 18.2).  Covers the two remaining sub-bull", "file_type": "rationale", "source_file": "backend/tests/test_mcp_log.py", "source_location": "L1"}, {"id": "tests_test_mcp_log_rationale_39", "label": "Ensure the schema (incl. the mcp_log table) exists in the temp DB.", "file_type": "rationale", "source_file": "backend/tests/test_mcp_log.py", "source_location": "L39"}, {"id": "tests_test_mcp_log_rationale_71", "label": "Logging is opt-in: a default registry must not write to the log.", "file_type": "rationale", "source_file": "backend/tests/test_mcp_log.py", "source_location": "L71"}, {"id": "tests_test_mcp_log_rationale_106", "label": "TestClient with lifespan active (creates schema in the temp DB).", "file_type": "rationale", "source_file": "backend/tests/test_mcp_log.py", "source_location": "L106"}], "edges": [{"source": "c_users_user_desktop_imaginehack_backend_tests_test_mcp_log_py", "target": "os", "relation": "imports", "context": "import", "confidence": "EXTRACTED", "source_file": "backend/tests/test_mcp_log.py", "source_location": "L17", "weight": 1.0}, {"source": "c_users_user_desktop_imaginehack_backend_tests_test_mcp_log_py", "target": "tempfile", "relation": "imports", "context": "import", "confidence": "EXTRACTED", "source_file": "backend/tests/test_mcp_log.py", "source_location": "L18", "weight": 1.0}, {"source": "c_users_user_desktop_imaginehack_backend_tests_test_mcp_log_py", "target": "backend_core_config", "relation": "imports_from", "context": "import", "confidence": "EXTRACTED", "source_file": "backend/tests/test_mcp_log.py", "source_location": "L24", "weight": 1.0}, {"source": "c_users_user_desktop_imaginehack_backend_tests_test_mcp_log_py", "target": "pytest", "relation": "imports", "context": "import", "confidence": "EXTRACTED", "source_file": "backend/tests/test_mcp_log.py", "source_location": "L28", "weight": 1.0}, {"source": "c_users_user_desktop_imaginehack_backend_tests_test_mcp_log_py", "target": "fastapi_testclient", "relation": "imports_from", "context": "import", "confidence": "EXTRACTED", "source_file": "backend/tests/test_mcp_log.py", "source_location": "L29", "weight": 1.0}, {"source": "c_users_user_desktop_imaginehack_backend_tests_test_mcp_log_py", "target": "backend_connectors", "relation": "imports_from", "context": "import", "confidence": "EXTRACTED", "source_file": "backend/tests/test_mcp_log.py", "source_location": "L31", "weight": 1.0}, {"source": "c_users_user_desktop_imaginehack_backend_tests_test_mcp_log_py", "target": "backend_core_database", "relation": "imports_from", "context": "import", "confidence": "EXTRACTED", "source_file": "backend/tests/test_mcp_log.py", "source_location": "L32", "weight": 1.0}, {"source": "c_users_user_desktop_imaginehack_backend_tests_test_mcp_log_py", "target": "backend_main", "relation": "imports_from", "context": "import", "confidence": "EXTRACTED", "source_file": "backend/tests/test_mcp_log.py", "source_location": "L33", "weight": 1.0}, {"source": "c_users_user_desktop_imaginehack_backend_tests_test_mcp_log_py", "target": "backend_services", "relation": "imports_from", "context": "import", "confidence": "EXTRACTED", "source_file": "backend/tests/test_mcp_log.py", "source_location": "L34", "weight": 1.0}, {"source": "c_users_user_desktop_imaginehack_backend_tests_test_mcp_log_py", "target": "tests_test_mcp_log_schema", "relation": "contains", "confidence": "EXTRACTED", "source_file": "backend/tests/test_mcp_log.py", "source_location": "L38", "weight": 1.0}, {"source": "c_users_user_desktop_imaginehack_backend_tests_test_mcp_log_py", "target": "tests_test_mcp_log_test_registry_execute_logs_connector_invocation", "relation": "contains", "confidence": "EXTRACTED", "source_file": "backend/tests/test_mcp_log.py", "source_location": "L46", "weight": 1.0}, {"source": "c_users_user_desktop_imaginehack_backend_tests_test_mcp_log_py", "target": "tests_test_mcp_log_test_registry_without_logging_does_not_record", "relation": "contains", "confidence": "EXTRACTED", "source_file": "backend/tests/test_mcp_log.py", "source_location": "L70", "weight": 1.0}, {"source": "c_users_user_desktop_imaginehack_backend_tests_test_mcp_log_py", "target": "tests_test_mcp_log_test_list_mcp_log_filters_by_workload_and_orders_recent_first", "relation": "contains", "confidence": "EXTRACTED", "source_file": "backend/tests/test_mcp_log.py", "source_location": "L80", "weight": 1.0}, {"source": "c_users_user_desktop_imaginehack_backend_tests_test_mcp_log_py", "target": "tests_test_mcp_log_client", "relation": "contains", "confidence": "EXTRACTED", "source_file": "backend/tests/test_mcp_log.py", "source_location": "L105", "weight": 1.0}, {"source": "c_users_user_desktop_imaginehack_backend_tests_test_mcp_log_py", "target": "tests_test_mcp_log_test_get_mcp_log_endpoint_returns_bare_list", "relation": "contains", "confidence": "EXTRACTED", "source_file": "backend/tests/test_mcp_log.py", "source_location": "L111", "weight": 1.0}, {"source": "c_users_user_desktop_imaginehack_backend_tests_test_mcp_log_py", "target": "tests_test_mcp_log_test_get_mcp_log_endpoint_filters_by_workload", "relation": "contains", "confidence": "EXTRACTED", "source_file": "backend/tests/test_mcp_log.py", "source_location": "L138", "weight": 1.0}, {"source": "tests_test_mcp_log_rationale_1", "target": "c_users_user_desktop_imaginehack_backend_tests_test_mcp_log_py", "relation": "rationale_for", "confidence": "EXTRACTED", "source_file": "backend/tests/test_mcp_log.py", "source_location": "L1", "weight": 1.0}, {"source": "tests_test_mcp_log_rationale_39", "target": "tests_test_mcp_log_schema", "relation": "rationale_for", "confidence": "EXTRACTED", "source_file": "backend/tests/test_mcp_log.py", "source_location": "L39", "weight": 1.0}, {"source": "tests_test_mcp_log_rationale_71", "target": "tests_test_mcp_log_test_registry_without_logging_does_not_record", "relation": "rationale_for", "confidence": "EXTRACTED", "source_file": "backend/tests/test_mcp_log.py", "source_location": "L71", "weight": 1.0}, {"source": "tests_test_mcp_log_rationale_106", "target": "tests_test_mcp_log_client", "relation": "rationale_for", "confidence": "EXTRACTED", "source_file": "backend/tests/test_mcp_log.py", "source_location": "L106", "weight": 1.0}], "raw_calls": [{"caller_nid": "tests_test_mcp_log_schema", "callee": "init_db", "is_member_call": false, "source_file": "C:\\Users\\User\\Desktop\\ImagineHack\\backend\\tests\\test_mcp_log.py", "source_location": "L40", "receiver": null}, {"caller_nid": "tests_test_mcp_log_test_registry_execute_logs_connector_invocation", "callee": "ConnectorRegistry", "is_member_call": false, "source_file": "C:\\Users\\User\\Desktop\\ImagineHack\\backend\\tests\\test_mcp_log.py", "source_location": "L47", "receiver": null}, {"caller_nid": "tests_test_mcp_log_test_registry_execute_logs_connector_invocation", "callee": "execute", "is_member_call": true, "source_file": "C:\\Users\\User\\Desktop\\ImagineHack\\backend\\tests\\test_mcp_log.py", "source_location": "L48", "receiver": null}, {"caller_nid": "tests_test_mcp_log_test_registry_execute_logs_connector_invocation", "callee": "list_mcp_log", "is_member_call": true, "source_file": "C:\\Users\\User\\Desktop\\ImagineHack\\backend\\tests\\test_mcp_log.py", "source_location": "L55", "receiver": null}, {"caller_nid": "tests_test_mcp_log_test_registry_execute_logs_connector_invocation", "callee": "get", "is_member_call": true, "source_file": "C:\\Users\\User\\Desktop\\ImagineHack\\backend\\tests\\test_mcp_log.py", "source_location": "L66", "receiver": null}, {"caller_nid": "tests_test_mcp_log_test_registry_without_logging_does_not_record", "callee": "ConnectorRegistry", "is_member_call": false, "source_file": "C:\\Users\\User\\Desktop\\ImagineHack\\backend\\tests\\test_mcp_log.py", "source_location": "L72", "receiver": null}, {"caller_nid": "tests_test_mcp_log_test_registry_without_logging_does_not_record", "callee": "execute", "is_member_call": true, "source_file": "C:\\Users\\User\\Desktop\\ImagineHack\\backend\\tests\\test_mcp_log.py", "source_location": "L73", "receiver": null}, {"caller_nid": "tests_test_mcp_log_test_registry_without_logging_does_not_record", "callee": "list_mcp_log", "is_member_call": true, "source_file": "C:\\Users\\User\\Desktop\\ImagineHack\\backend\\tests\\test_mcp_log.py", "source_location": "L74", "receiver": null}, {"caller_nid": "tests_test_mcp_log_test_list_mcp_log_filters_by_workload_and_orders_recent_first", "callee": "ConnectorRegistry", "is_member_call": false, "source_file": "C:\\Users\\User\\Desktop\\ImagineHack\\backend\\tests\\test_mcp_log.py", "source_location": "L81", "receiver": null}, {"caller_nid": "tests_test_mcp_log_test_list_mcp_log_filters_by_workload_and_orders_recent_first", "callee": "execute", "is_member_call": true, "source_file": "C:\\Users\\User\\Desktop\\ImagineHack\\backend\\tests\\test_mcp_log.py", "source_location": "L83", "receiver": null}, {"caller_nid": "tests_test_mcp_log_test_list_mcp_log_filters_by_workload_and_orders_recent_first", "callee": "execute", "is_member_call": true, "source_file": "C:\\Users\\User\\Desktop\\ImagineHack\\backend\\tests\\test_mcp_log.py", "source_location": "L84", "receiver": null}, {"caller_nid": "tests_test_mcp_log_test_list_mcp_log_filters_by_workload_and_orders_recent_first", "callee": "execute", "is_member_call": true, "source_file": "C:\\Users\\User\\Desktop\\ImagineHack\\backend\\tests\\test_mcp_log.py", "source_location": "L86", "receiver": null}, {"caller_nid": "tests_test_mcp_log_test_list_mcp_log_filters_by_workload_and_orders_recent_first", "callee": "list_mcp_log", "is_member_call": true, "source_file": "C:\\Users\\User\\Desktop\\ImagineHack\\backend\\tests\\test_mcp_log.py", "source_location": "L88", "receiver": null}, {"caller_nid": "tests_test_mcp_log_test_list_mcp_log_filters_by_workload_and_orders_recent_first", "callee": "list_mcp_log", "is_member_call": true, "source_file": "C:\\Users\\User\\Desktop\\ImagineHack\\backend\\tests\\test_mcp_log.py", "source_location": "L93", "receiver": null}, {"caller_nid": "tests_test_mcp_log_test_list_mcp_log_filters_by_workload_and_orders_recent_first", "callee": "list_mcp_log", "is_member_call": true, "source_file": "C:\\Users\\User\\Desktop\\ImagineHack\\backend\\tests\\test_mcp_log.py", "source_location": "L97", "receiver": null}, {"caller_nid": "tests_test_mcp_log_client", "callee": "TestClient", "is_member_call": false, "source_file": "C:\\Users\\User\\Desktop\\ImagineHack\\backend\\tests\\test_mcp_log.py", "source_location": "L107", "receiver": null}, {"caller_nid": "tests_test_mcp_log_test_get_mcp_log_endpoint_returns_bare_list", "callee": "ConnectorRegistry", "is_member_call": false, "source_file": "C:\\Users\\User\\Desktop\\ImagineHack\\backend\\tests\\test_mcp_log.py", "source_location": "L112", "receiver": null}, {"caller_nid": "tests_test_mcp_log_test_get_mcp_log_endpoint_returns_bare_list", "callee": "execute", "is_member_call": true, "source_file": "C:\\Users\\User\\Desktop\\ImagineHack\\backend\\tests\\test_mcp_log.py", "source_location": "L113", "receiver": null}, {"caller_nid": "tests_test_mcp_log_test_get_mcp_log_endpoint_returns_bare_list", "callee": "execute", "is_member_call": true, "source_file": "C:\\Users\\User\\Desktop\\ImagineHack\\backend\\tests\\test_mcp_log.py", "source_location": "L114", "receiver": null}, {"caller_nid": "tests_test_mcp_log_test_get_mcp_log_endpoint_returns_bare_list", "callee": "get", "is_member_call": true, "source_file": "C:\\Users\\User\\Desktop\\ImagineHack\\backend\\tests\\test_mcp_log.py", "source_location": "L116", "receiver": null}, {"caller_nid": "tests_test_mcp_log_test_get_mcp_log_endpoint_returns_bare_list", "callee": "json", "is_member_call": true, "source_file": "C:\\Users\\User\\Desktop\\ImagineHack\\backend\\tests\\test_mcp_log.py", "source_location": "L118", "receiver": null}, {"caller_nid": "tests_test_mcp_log_test_get_mcp_log_endpoint_returns_bare_list", "callee": "keys", "is_member_call": true, "source_file": "C:\\Users\\User\\Desktop\\ImagineHack\\backend\\tests\\test_mcp_log.py", "source_location": "L126", "receiver": null}, {"caller_nid": "tests_test_mcp_log_test_get_mcp_log_endpoint_filters_by_workload", "callee": "ConnectorRegistry", "is_member_call": false, "source_file": "C:\\Users\\User\\Desktop\\ImagineHack\\backend\\tests\\test_mcp_log.py", "source_location": "L139", "receiver": null}, {"caller_nid": "tests_test_mcp_log_test_get_mcp_log_endpoint_filters_by_workload", "callee": "execute", "is_member_call": true, "source_file": "C:\\Users\\User\\Desktop\\ImagineHack\\backend\\tests\\test_mcp_log.py", "source_location": "L140", "receiver": null}, {"caller_nid": "tests_test_mcp_log_test_get_mcp_log_endpoint_filters_by_workload", "callee": "get", "is_member_call": true, "source_file": "C:\\Users\\User\\Desktop\\ImagineHack\\backend\\tests\\test_mcp_log.py", "source_location": "L142", "receiver": null}, {"caller_nid": "tests_test_mcp_log_test_get_mcp_log_endpoint_filters_by_workload", "callee": "json", "is_member_call": true, "source_file": "C:\\Users\\User\\Desktop\\ImagineHack\\backend\\tests\\test_mcp_log.py", "source_location": "L144", "receiver": null}]}